dynamodb_garbage_collector.py
dynamodb_garbage_collector-1.1.0.dist-info/LICENSE
dynamodb_garbage_collector-1.1.0.dist-info/METADATA
dynamodb_garbage_collector-1.1.0.dist-info/WHEEL
dynamodb_garbage_collector-1.1.0.dist-info/RECORD
