Metadata-Version: 2.1
Name: dynamodb-garbage-collector
Version: 1.1.0
Summary: Remove garbage items from DynamoDB tables
License: MIT
Author: Marçal Pla
Author-email: marcal.pla@shimoku.com
Requires-Python: >=3.9,<4.0
Classifier: License :: OSI Approved :: MIT License
Classifier: Programming Language :: Python :: 3
Classifier: Programming Language :: Python :: 3.9
Classifier: Programming Language :: Python :: 3.10
Classifier: Programming Language :: Python :: 3.11
Requires-Dist: boto3 (>=1.26.41,<2.0.0)
Requires-Dist: botocore (>=1.29.41,<2.0.0)
